grooming/__init__.py
grooming/lemma.py
grooming/txt.py
grooming-0.5.dist-info/METADATA
grooming-0.5.dist-info/WHEEL
grooming-0.5.dist-info/top_level.txt
grooming-0.5.dist-info/RECORD
